fields_local/__init__.py
fields_local/constants_src_field_local.py
fields_local/constants_src_fields_local.py
fields_local/field_local.py
fields_local/fields_local.py
fields_local-0.0.13.dist-info/METADATA
fields_local-0.0.13.dist-info/WHEEL
fields_local-0.0.13.dist-info/top_level.txt
fields_local-0.0.13.dist-info/RECORD
