Metadata-Version: 2.4
Name: fields-local
Version: 0.0.13
Summary: PyPI Package for Circles fields-local Python
Home-page: https://github.com/circles-zone/fields-local-python-package
Author: Circles
Author-email: info@circlez.ai
Classifier: Programming Language :: Python :: 3
Classifier: Operating System :: OS Independent
Requires-Dist: python-sdk-remote==0.0.145
Requires-Dist: logger-local>=0.0.178
Requires-Dist: database-mysql-local>=0.1.10
Dynamic: author
Dynamic: author-email
Dynamic: classifier
Dynamic: description
Dynamic: description-content-type
Dynamic: home-page
Dynamic: requires-dist
Dynamic: summary
